{"kind":"blogger#postList","items":[{"author":{"displayName":"Free Game Puzzles","id":"12243895325069569914","image":{"url":"//www.blogger.com/img/blogger_logo_round_35.png"},"url":"https://www.blogger.com/profile/12243895325069569914"},"blog":{"id":"1204956684090030699"},"content":"","etag":"\"dGltZXN0YW1wOiAxNjEyMjUzODQwNjc2Cm9mZnNldDogLTI4ODAwMDAwCg\"","id":"8091797478807557951","kind":"blogger#post","published":"2021-01-14T07:05:00-08:00","replies":{"selfLink":"https://www.googleapis.com/blogger/v3/blogs/1204956684090030699/posts/8091797478807557951/comments","totalItems":"0"},"selfLink":"https://www.googleapis.com/blogger/v3/blogs/1204956684090030699/posts/8091797478807557951","title":"Antefix","updated":"2021-02-02T00:17:20-08:00","url":"http://buildingconstructionbl.blogspot.com/2021/01/antefix.html"},{"author":{"displayName":"Free Game Puzzles","id":"12243895325069569914","image":{"url":"//www.blogger.com/img/blogger_logo_round_35.png"},"url":"https://www.blogger.com/profile/12243895325069569914"},"blog":{"id":"1204956684090030699"},"content":"","etag":"\"dGltZXN0YW1wOiAxNjE1MjI0Nzg2MjgyCm9mZnNldDogLTI4ODAwMDAwCg\"","id":"7325898844012676339","kind":"blogger#post","published":"2021-01-14T06:57:00-08:00","replies":{"selfLink":"https://www.googleapis.com/blogger/v3/blogs/1204956684090030699/posts/7325898844012676339/comments","totalItems":"0"},"selfLink":"https://www.googleapis.com/blogger/v3/blogs/1204956684090030699/posts/7325898844012676339","title":"Arch","updated":"2021-03-08T09:33:06-08:00","url":"http://buildingconstructionbl.blogspot.com/2021/01/arch.html"},{"author":{"displayName":"Free Game Puzzles","id":"12243895325069569914","image":{"url":"//www.blogger.com/img/blogger_logo_round_35.png"},"url":"https://www.blogger.com/profile/12243895325069569914"},"blog":{"id":"1204956684090030699"},"content":"","etag":"\"dGltZXN0YW1wOiAxNjEyMzM3NDA1ODQ5Cm9mZnNldDogLTI4ODAwMDAwCg\"","id":"8150239832982884099","kind":"blogger#post","published":"2021-01-13T11:05:00-08:00","replies":{"selfLink":"https://www.googleapis.com/blogger/v3/blogs/1204956684090030699/posts/8150239832982884099/comments","totalItems":"0"},"selfLink":"https://www.googleapis.com/blogger/v3/blogs/1204956684090030699/posts/8150239832982884099","title":"Flying buttress","updated":"2021-02-02T23:30:05-08:00","url":"http://buildingconstructionbl.blogspot.com/2021/01/flying-buttress.html"},{"author":{"displayName":"Free Game Puzzles","id":"12243895325069569914","image":{"url":"//www.blogger.com/img/blogger_logo_round_35.png"},"url":"https://www.blogger.com/profile/12243895325069569914"},"blog":{"id":"1204956684090030699"},"content":"","etag":"\"dGltZXN0YW1wOiAxNjEwNTY0MjA1NjY1Cm9mZnNldDogLTI4ODAwMDAwCg\"","id":"2965970659396789446","kind":"blogger#post","published":"2021-01-13T10:56:00-08:00","replies":{"selfLink":"https://www.googleapis.com/blogger/v3/blogs/1204956684090030699/posts/2965970659396789446/comments","totalItems":"0"},"selfLink":"https://www.googleapis.com/blogger/v3/blogs/1204956684090030699/posts/2965970659396789446","title":"Archivolt","updated":"2021-01-13T10:56:45-08:00","url":"http://buildingconstructionbl.blogspot.com/2021/01/archivolt.html"},{"author":{"displayName":"Free Game Puzzles","id":"12243895325069569914","image":{"url":"//www.blogger.com/img/blogger_logo_round_35.png"},"url":"https://www.blogger.com/profile/12243895325069569914"},"blog":{"id":"1204956684090030699"},"content":"","etag":"\"dGltZXN0YW1wOiAxNjEwNTY0MDQwOTk2Cm9mZnNldDogLTI4ODAwMDAwCg\"","id":"2880167993345794645","kind":"blogger#post","published":"2021-01-13T10:54:00-08:00","replies":{"selfLink":"https://www.googleapis.com/blogger/v3/blogs/1204956684090030699/posts/2880167993345794645/comments","totalItems":"0"},"selfLink":"https://www.googleapis.com/blogger/v3/blogs/1204956684090030699/posts/2880167993345794645","title":"Balcony","updated":"2021-01-13T10:54:00-08:00","url":"http://buildingconstructionbl.blogspot.com/2021/01/balcony.html"},{"author":{"displayName":"Free Game Puzzles","id":"12243895325069569914","image":{"url":"//www.blogger.com/img/blogger_logo_round_35.png"},"url":"https://www.blogger.com/profile/12243895325069569914"},"blog":{"id":"1204956684090030699"},"content":"","etag":"\"dGltZXN0YW1wOiAxNjE1MjI1MTY4MzQxCm9mZnNldDogLTI4ODAwMDAwCg\"","id":"5329935585042802859","kind":"blogger#post","published":"2021-01-13T10:50:00-08:00","replies":{"selfLink":"https://www.googleapis.com/blogger/v3/blogs/1204956684090030699/posts/5329935585042802859/comments","totalItems":"0"},"selfLink":"https://www.googleapis.com/blogger/v3/blogs/1204956684090030699/posts/5329935585042802859","title":"Baluster","updated":"2021-03-08T09:39:28-08:00","url":"http://buildingconstructionbl.blogspot.com/2021/01/baluster.html"},{"author":{"displayName":"Free Game Puzzles","id":"12243895325069569914","image":{"url":"//www.blogger.com/img/blogger_logo_round_35.png"},"url":"https://www.blogger.com/profile/12243895325069569914"},"blog":{"id":"1204956684090030699"},"content":"","etag":"\"dGltZXN0YW1wOiAxNjE1MjI1MzIxMDUyCm9mZnNldDogLTI4ODAwMDAwCg\"","id":"6485115748468554298","kind":"blogger#post","published":"2021-01-13T10:47:00-08:00","replies":{"selfLink":"https://www.googleapis.com/blogger/v3/blogs/1204956684090030699/posts/6485115748468554298/comments","totalItems":"0"},"selfLink":"https://www.googleapis.com/blogger/v3/blogs/1204956684090030699/posts/6485115748468554298","title":"Bochka roof","updated":"2021-03-08T09:42:01-08:00","url":"http://buildingconstructionbl.blogspot.com/2021/01/bochka-roof.html"},{"author":{"displayName":"Free Game Puzzles","id":"12243895325069569914","image":{"url":"//www.blogger.com/img/blogger_logo_round_35.png"},"url":"https://www.blogger.com/profile/12243895325069569914"},"blog":{"id":"1204956684090030699"},"content":"","etag":"\"dGltZXN0YW1wOiAxNjE1MjI1NDg2NTE4Cm9mZnNldDogLTI4ODAwMDAwCg\"","id":"8853832541620876581","kind":"blogger#post","published":"2021-01-13T10:44:00-08:00","replies":{"selfLink":"https://www.googleapis.com/blogger/v3/blogs/1204956684090030699/posts/8853832541620876581/comments","totalItems":"0"},"selfLink":"https://www.googleapis.com/blogger/v3/blogs/1204956684090030699/posts/8853832541620876581","title":" Octagon house","updated":"2021-03-08T09:44:46-08:00","url":"http://buildingconstructionbl.blogspot.com/2021/01/octagon-house.html"},{"author":{"displayName":"Free Game Puzzles","id":"12243895325069569914","image":{"url":"//www.blogger.com/img/blogger_logo_round_35.png"},"url":"https://www.blogger.com/profile/12243895325069569914"},"blog":{"id":"1204956684090030699"},"content":"","etag":"\"dGltZXN0YW1wOiAxNjEwNTYzMzAzMjc4Cm9mZnNldDogLTI4ODAwMDAwCg\"","id":"7182737591384049816","kind":"blogger#post","published":"2021-01-13T10:41:00-08:00","replies":{"selfLink":"https://www.googleapis.com/blogger/v3/blogs/1204956684090030699/posts/7182737591384049816/comments","totalItems":"0"},"selfLink":"https://www.googleapis.com/blogger/v3/blogs/1204956684090030699/posts/7182737591384049816","title":"Geodesic dome","updated":"2021-01-13T10:41:43-08:00","url":"http://buildingconstructionbl.blogspot.com/2021/01/geodesic-dome.html"},{"author":{"displayName":"Free Game Puzzles","id":"12243895325069569914","image":{"url":"//www.blogger.com/img/blogger_logo_round_35.png"},"url":"https://www.blogger.com/profile/12243895325069569914"},"blog":{"id":"1204956684090030699"},"content":"","etag":"\"dGltZXN0YW1wOiAxNjE1MjI1NjcxNTE0Cm9mZnNldDogLTI4ODAwMDAwCg\"","id":"3733713244003270767","kind":"blogger#post","published":"2021-01-13T10:36:00-08:00","replies":{"selfLink":"https://www.googleapis.com/blogger/v3/blogs/1204956684090030699/posts/3733713244003270767/comments","totalItems":"0"},"selfLink":"https://www.googleapis.com/blogger/v3/blogs/1204956684090030699/posts/3733713244003270767","title":"City gate","updated":"2021-03-08T09:47:51-08:00","url":"http://buildingconstructionbl.blogspot.com/2021/01/city-gate.html"},{"author":{"displayName":"Free Game Puzzles","id":"12243895325069569914","image":{"url":"//www.blogger.com/img/blogger_logo_round_35.png"},"url":"https://www.blogger.com/profile/12243895325069569914"},"blog":{"id":"1204956684090030699"},"content":"","etag":"\"dGltZXN0YW1wOiAxNjE1MjY4Njg0MDUxCm9mZnNldDogLTI4ODAwMDAwCg\"","id":"1326869778074399731","kind":"blogger#post","published":"2021-01-13T10:33:00-08:00","replies":{"selfLink":"https://www.googleapis.com/blogger/v3/blogs/1204956684090030699/posts/1326869778074399731/comments","totalItems":"0"},"selfLink":"https://www.googleapis.com/blogger/v3/blogs/1204956684090030699/posts/1326869778074399731","title":"I-beam","updated":"2021-03-08T21:44:44-08:00","url":"http://buildingconstructionbl.blogspot.com/2021/01/i-beam.html"},{"author":{"displayName":"Free Game Puzzles","id":"12243895325069569914","image":{"url":"//www.blogger.com/img/blogger_logo_round_35.png"},"url":"https://www.blogger.com/profile/12243895325069569914"},"blog":{"id":"1204956684090030699"},"content":"","etag":"\"dGltZXN0YW1wOiAxNjE1MjY4ODAzMDkxCm9mZnNldDogLTI4ODAwMDAwCg\"","id":"7987866016706903188","kind":"blogger#post","published":"2021-01-13T10:27:00-08:00","replies":{"selfLink":"https://www.googleapis.com/blogger/v3/blogs/1204956684090030699/posts/7987866016706903188/comments","totalItems":"0"},"selfLink":"https://www.googleapis.com/blogger/v3/blogs/1204956684090030699/posts/7987866016706903188","title":"Orifice plate","updated":"2021-03-08T21:46:43-08:00","url":"http://buildingconstructionbl.blogspot.com/2021/01/orifice-plate.html"},{"author":{"displayName":"Free Game Puzzles","id":"12243895325069569914","image":{"url":"//www.blogger.com/img/blogger_logo_round_35.png"},"url":"https://www.blogger.com/profile/12243895325069569914"},"blog":{"id":"1204956684090030699"},"content":"","etag":"\"dGltZXN0YW1wOiAxNjE1MjY5MDQyNjAwCm9mZnNldDogLTI4ODAwMDAwCg\"","id":"3129568583260577102","kind":"blogger#post","published":"2021-01-13T10:18:00-08:00","replies":{"selfLink":"https://www.googleapis.com/blogger/v3/blogs/1204956684090030699/posts/3129568583260577102/comments","totalItems":"0"},"selfLink":"https://www.googleapis.com/blogger/v3/blogs/1204956684090030699/posts/3129568583260577102","title":"Keystone (architecture)","updated":"2021-03-08T21:50:42-08:00","url":"http://buildingconstructionbl.blogspot.com/2021/01/keystone-architecture.html"},{"author":{"displayName":"Free Game Puzzles","id":"12243895325069569914","image":{"url":"//www.blogger.com/img/blogger_logo_round_35.png"},"url":"https://www.blogger.com/profile/12243895325069569914"},"blog":{"id":"1204956684090030699"},"content":"","etag":"\"dGltZXN0YW1wOiAxNjE1MjY5MTU3ODc5Cm9mZnNldDogLTI4ODAwMDAwCg\"","id":"6587227561189721749","kind":"blogger#post","published":"2021-01-13T10:16:00-08:00","replies":{"selfLink":"https://www.googleapis.com/blogger/v3/blogs/1204956684090030699/posts/6587227561189721749/comments","totalItems":"0"},"selfLink":"https://www.googleapis.com/blogger/v3/blogs/1204956684090030699/posts/6587227561189721749","title":"Wicket gate","updated":"2021-03-08T21:52:37-08:00","url":"http://buildingconstructionbl.blogspot.com/2021/01/wicket-gate.html"},{"author":{"displayName":"Free Game Puzzles","id":"12243895325069569914","image":{"url":"//www.blogger.com/img/blogger_logo_round_35.png"},"url":"https://www.blogger.com/profile/12243895325069569914"},"blog":{"id":"1204956684090030699"},"content":"","etag":"\"dGltZXN0YW1wOiAxNjE1MjY5MzczMDkwCm9mZnNldDogLTI4ODAwMDAwCg\"","id":"4006596151367933203","kind":"blogger#post","published":"2021-01-13T10:12:00-08:00","replies":{"selfLink":"https://www.googleapis.com/blogger/v3/blogs/1204956684090030699/posts/4006596151367933203/comments","totalItems":"0"},"selfLink":"https://www.googleapis.com/blogger/v3/blogs/1204956684090030699/posts/4006596151367933203","title":"Capital (architecture)","updated":"2021-03-08T21:56:13-08:00","url":"http://buildingconstructionbl.blogspot.com/2021/01/capital-architecture.html"},{"author":{"displayName":"Free Game Puzzles","id":"12243895325069569914","image":{"url":"//www.blogger.com/img/blogger_logo_round_35.png"},"url":"https://www.blogger.com/profile/12243895325069569914"},"blog":{"id":"1204956684090030699"},"content":"","etag":"\"dGltZXN0YW1wOiAxNjE1MjY5NTA2NzYxCm9mZnNldDogLTI4ODAwMDAwCg\"","id":"354782157196152537","kind":"blogger#post","published":"2021-01-13T09:51:00-08:00","replies":{"selfLink":"https://www.googleapis.com/blogger/v3/blogs/1204956684090030699/posts/354782157196152537/comments","totalItems":"0"},"selfLink":"https://www.googleapis.com/blogger/v3/blogs/1204956684090030699/posts/354782157196152537","title":"Cornice","updated":"2021-03-08T21:58:26-08:00","url":"http://buildingconstructionbl.blogspot.com/2021/01/cornice.html"},{"author":{"displayName":"Free Game Puzzles","id":"12243895325069569914","image":{"url":"//www.blogger.com/img/blogger_logo_round_35.png"},"url":"https://www.blogger.com/profile/12243895325069569914"},"blog":{"id":"1204956684090030699"},"content":"","etag":"\"dGltZXN0YW1wOiAxNjE1MjY5NjY5Mzg0Cm9mZnNldDogLTI4ODAwMDAwCg\"","id":"4048488046499689043","kind":"blogger#post","published":"2021-01-13T09:48:00-08:00","replies":{"selfLink":"https://www.googleapis.com/blogger/v3/blogs/1204956684090030699/posts/4048488046499689043/comments","totalItems":"0"},"selfLink":"https://www.googleapis.com/blogger/v3/blogs/1204956684090030699/posts/4048488046499689043","title":"Coffer","updated":"2021-03-08T22:01:09-08:00","url":"http://buildingconstructionbl.blogspot.com/2021/01/coffer.html"},{"author":{"displayName":"Free Game Puzzles","id":"12243895325069569914","image":{"url":"//www.blogger.com/img/blogger_logo_round_35.png"},"url":"https://www.blogger.com/profile/12243895325069569914"},"blog":{"id":"1204956684090030699"},"content":"","etag":"\"dGltZXN0YW1wOiAxNjE1MjY5Nzk0MDE0Cm9mZnNldDogLTI4ODAwMDAwCg\"","id":"8363347474773346256","kind":"blogger#post","published":"2021-01-13T07:46:00-08:00","replies":{"selfLink":"https://www.googleapis.com/blogger/v3/blogs/1204956684090030699/posts/8363347474773346256/comments","totalItems":"0"},"selfLink":"https://www.googleapis.com/blogger/v3/blogs/1204956684090030699/posts/8363347474773346256","title":"Guard stone","updated":"2021-03-08T22:03:14-08:00","url":"http://buildingconstructionbl.blogspot.com/2021/01/guard-stone.html"},{"author":{"displayName":"Free Game Puzzles","id":"12243895325069569914","image":{"url":"//www.blogger.com/img/blogger_logo_round_35.png"},"url":"https://www.blogger.com/profile/12243895325069569914"},"blog":{"id":"1204956684090030699"},"content":"","etag":"\"dGltZXN0YW1wOiAxNjE1MjY5ODgwOTYzCm9mZnNldDogLTI4ODAwMDAwCg\"","id":"4907176100408840245","kind":"blogger#post","published":"2021-01-13T07:43:00-08:00","replies":{"selfLink":"https://www.googleapis.com/blogger/v3/blogs/1204956684090030699/posts/4907176100408840245/comments","totalItems":"0"},"selfLink":"https://www.googleapis.com/blogger/v3/blogs/1204956684090030699/posts/4907176100408840245","title":"Buttress","updated":"2021-03-08T22:04:40-08:00","url":"http://buildingconstructionbl.blogspot.com/2021/01/buttress.html"},{"author":{"displayName":"Free Game Puzzles","id":"12243895325069569914","image":{"url":"//www.blogger.com/img/blogger_logo_round_35.png"},"url":"https://www.blogger.com/profile/12243895325069569914"},"blog":{"id":"1204956684090030699"},"content":"","etag":"\"dGltZXN0YW1wOiAxNjE1MjY5OTczNjQyCm9mZnNldDogLTI4ODAwMDAwCg\"","id":"4219255260029086093","kind":"blogger#post","published":"2021-01-13T07:39:00-08:00","replies":{"selfLink":"https://www.googleapis.com/blogger/v3/blogs/1204956684090030699/posts/4219255260029086093/comments","totalItems":"0"},"selfLink":"https://www.googleapis.com/blogger/v3/blogs/1204956684090030699/posts/4219255260029086093","title":"Cornerstone","updated":"2021-03-08T22:06:13-08:00","url":"http://buildingconstructionbl.blogspot.com/2021/01/cornerstone.html"},{"author":{"displayName":"Free Game Puzzles","id":"12243895325069569914","image":{"url":"//www.blogger.com/img/blogger_logo_round_35.png"},"url":"https://www.blogger.com/profile/12243895325069569914"},"blog":{"id":"1204956684090030699"},"content":"","etag":"\"dGltZXN0YW1wOiAxNjE1MjcwMDYxNjQwCm9mZnNldDogLTI4ODAwMDAwCg\"","id":"1009344890704880228","kind":"blogger#post","published":"2021-01-13T07:35:00-08:00","replies":{"selfLink":"https://www.googleapis.com/blogger/v3/blogs/1204956684090030699/posts/1009344890704880228/comments","totalItems":"0"},"selfLink":"https://www.googleapis.com/blogger/v3/blogs/1204956684090030699/posts/1009344890704880228","title":"Bracket (architecture)","updated":"2021-03-08T22:07:41-08:00","url":"http://buildingconstructionbl.blogspot.com/2021/01/bracket-architecture.html"},{"author":{"displayName":"Free Game Puzzles","id":"12243895325069569914","image":{"url":"//www.blogger.com/img/blogger_logo_round_35.png"},"url":"https://www.blogger.com/profile/12243895325069569914"},"blog":{"id":"1204956684090030699"},"content":"","etag":"\"dGltZXN0YW1wOiAxNjE1MjcwMTYzNzMyCm9mZnNldDogLTI4ODAwMDAwCg\"","id":"6658172959554197206","kind":"blogger#post","published":"2021-01-13T07:30:00-08:00","replies":{"selfLink":"https://www.googleapis.com/blogger/v3/blogs/1204956684090030699/posts/6658172959554197206/comments","totalItems":"0"},"selfLink":"https://www.googleapis.com/blogger/v3/blogs/1204956684090030699/posts/6658172959554197206","title":"Porch","updated":"2021-03-08T22:09:23-08:00","url":"http://buildingconstructionbl.blogspot.com/2021/01/porch.html"},{"author":{"displayName":"Free Game Puzzles","id":"12243895325069569914","image":{"url":"//www.blogger.com/img/blogger_logo_round_35.png"},"url":"https://www.blogger.com/profile/12243895325069569914"},"blog":{"id":"1204956684090030699"},"content":"","etag":"\"dGltZXN0YW1wOiAxNjE1MjcwMzY1MDQ5Cm9mZnNldDogLTI4ODAwMDAwCg\"","id":"2628051119569665923","kind":"blogger#post","published":"2021-01-13T07:21:00-08:00","replies":{"selfLink":"https://www.googleapis.com/blogger/v3/blogs/1204956684090030699/posts/2628051119569665923/comments","totalItems":"0"},"selfLink":"https://www.googleapis.com/blogger/v3/blogs/1204956684090030699/posts/2628051119569665923","title":"Dome","updated":"2021-03-08T22:12:45-08:00","url":"http://buildingconstructionbl.blogspot.com/2021/01/dome.html"},{"author":{"displayName":"Free Game Puzzles","id":"12243895325069569914","image":{"url":"//www.blogger.com/img/blogger_logo_round_35.png"},"url":"https://www.blogger.com/profile/12243895325069569914"},"blog":{"id":"1204956684090030699"},"content":"","etag":"\"dGltZXN0YW1wOiAxNjE1MjcwNTYyODQ3Cm9mZnNldDogLTI4ODAwMDAwCg\"","id":"1050172806440376329","kind":"blogger#post","published":"2021-01-13T07:01:00-08:00","replies":{"selfLink":"https://www.googleapis.com/blogger/v3/blogs/1204956684090030699/posts/1050172806440376329/comments","totalItems":"0"},"selfLink":"https://www.googleapis.com/blogger/v3/blogs/1204956684090030699/posts/1050172806440376329","title":"Lesene","updated":"2021-03-08T22:16:02-08:00","url":"http://buildingconstructionbl.blogspot.com/2021/01/lesene.html"},{"author":{"displayName":"Free Game Puzzles","id":"12243895325069569914","image":{"url":"//www.blogger.com/img/blogger_logo_round_35.png"},"url":"https://www.blogger.com/profile/12243895325069569914"},"blog":{"id":"1204956684090030699"},"content":"","etag":"\"dGltZXN0YW1wOiAxNjExOTkyMDEwMDk0Cm9mZnNldDogLTI4ODAwMDAwCg\"","id":"3943907575007142807","kind":"blogger#post","published":"2021-01-13T06:53:00-08:00","replies":{"selfLink":"https://www.googleapis.com/blogger/v3/blogs/1204956684090030699/posts/3943907575007142807/comments","totalItems":"0"},"selfLink":"https://www.googleapis.com/blogger/v3/blogs/1204956684090030699/posts/3943907575007142807","title":"Self-framing metal buildings","updated":"2021-01-29T23:33:30-08:00","url":"http://buildingconstructionbl.blogspot.com/2021/01/self-framing-metal-buildings.html"},{"author":{"displayName":"Free Game Puzzles","id":"12243895325069569914","image":{"url":"//www.blogger.com/img/blogger_logo_round_35.png"},"url":"https://www.blogger.com/profile/12243895325069569914"},"blog":{"id":"1204956684090030699"},"content":"","etag":"\"dGltZXN0YW1wOiAxNjE1MjcxNDYyODAwCm9mZnNldDogLTI4ODAwMDAwCg\"","id":"7490388089549568823","kind":"blogger#post","published":"2021-01-13T06:46:00-08:00","replies":{"selfLink":"https://www.googleapis.com/blogger/v3/blogs/1204956684090030699/posts/7490388089549568823/comments","totalItems":"0"},"selfLink":"https://www.googleapis.com/blogger/v3/blogs/1204956684090030699/posts/7490388089549568823","title":"Lunette","updated":"2021-03-08T22:31:02-08:00","url":"http://buildingconstructionbl.blogspot.com/2021/01/lunette.html"},{"author":{"displayName":"Free Game Puzzles","id":"12243895325069569914","image":{"url":"//www.blogger.com/img/blogger_logo_round_35.png"},"url":"https://www.blogger.com/profile/12243895325069569914"},"blog":{"id":"1204956684090030699"},"content":"","etag":"\"dGltZXN0YW1wOiAxNjE1MjcxNTY3MjA4Cm9mZnNldDogLTI4ODAwMDAwCg\"","id":"4127708219560082044","kind":"blogger#post","published":"2021-01-12T00:10:00-08:00","replies":{"selfLink":"https://www.googleapis.com/blogger/v3/blogs/1204956684090030699/posts/4127708219560082044/comments","totalItems":"0"},"selfLink":"https://www.googleapis.com/blogger/v3/blogs/1204956684090030699/posts/4127708219560082044","title":"Wall plate","updated":"2021-03-08T22:32:47-08:00","url":"http://buildingconstructionbl.blogspot.com/2021/01/wall-plate.html"},{"author":{"displayName":"Free Game Puzzles","id":"12243895325069569914","image":{"url":"//www.blogger.com/img/blogger_logo_round_35.png"},"url":"https://www.blogger.com/profile/12243895325069569914"},"blog":{"id":"1204956684090030699"},"content":"","etag":"\"dGltZXN0YW1wOiAxNjE1MjcxNzIyOTI5Cm9mZnNldDogLTI4ODAwMDAwCg\"","id":"1707445535585534713","kind":"blogger#post","published":"2021-01-11T23:59:00-08:00","replies":{"selfLink":"https://www.googleapis.com/blogger/v3/blogs/1204956684090030699/posts/1707445535585534713/comments","totalItems":"0"},"selfLink":"https://www.googleapis.com/blogger/v3/blogs/1204956684090030699/posts/1707445535585534713","title":"Canopy (building)","updated":"2021-03-08T22:35:22-08:00","url":"http://buildingconstructionbl.blogspot.com/2021/01/canopy-building.html"},{"author":{"displayName":"Free Game Puzzles","id":"12243895325069569914","image":{"url":"//www.blogger.com/img/blogger_logo_round_35.png"},"url":"https://www.blogger.com/profile/12243895325069569914"},"blog":{"id":"1204956684090030699"},"content":"","etag":"\"dGltZXN0YW1wOiAxNjExOTkyMDc4NjE4Cm9mZnNldDogLTI4ODAwMDAwCg\"","id":"5596076489728671429","kind":"blogger#post","published":"2021-01-11T23:53:00-08:00","replies":{"selfLink":"https://www.googleapis.com/blogger/v3/blogs/1204956684090030699/posts/5596076489728671429/comments","totalItems":"0"},"selfLink":"https://www.googleapis.com/blogger/v3/blogs/1204956684090030699/posts/5596076489728671429","title":"Structural system","updated":"2021-01-29T23:34:38-08:00","url":"http://buildingconstructionbl.blogspot.com/2021/01/structural-system.html"},{"author":{"displayName":"Free Game Puzzles","id":"12243895325069569914","image":{"url":"//www.blogger.com/img/blogger_logo_round_35.png"},"url":"https://www.blogger.com/profile/12243895325069569914"},"blog":{"id":"1204956684090030699"},"content":"","etag":"\"dGltZXN0YW1wOiAxNjE1MjcxODMxNzM1Cm9mZnNldDogLTI4ODAwMDAwCg\"","id":"1220480639900799239","kind":"blogger#post","published":"2021-01-11T23:50:00-08:00","replies":{"selfLink":"https://www.googleapis.com/blogger/v3/blogs/1204956684090030699/posts/1220480639900799239/comments","totalItems":"0"},"selfLink":"https://www.googleapis.com/blogger/v3/blogs/1204956684090030699/posts/1220480639900799239","title":"Lath","updated":"2021-03-08T22:37:11-08:00","url":"http://buildingconstructionbl.blogspot.com/2021/01/lath.html"},{"author":{"displayName":"Free Game Puzzles","id":"12243895325069569914","image":{"url":"//www.blogger.com/img/blogger_logo_round_35.png"},"url":"https://www.blogger.com/profile/12243895325069569914"},"blog":{"id":"1204956684090030699"},"content":"","etag":"\"dGltZXN0YW1wOiAxNjE1MjcxOTA0MTc1Cm9mZnNldDogLTI4ODAwMDAwCg\"","id":"8378987530404431634","kind":"blogger#post","published":"2021-01-11T23:47:00-08:00","replies":{"selfLink":"https://www.googleapis.com/blogger/v3/blogs/1204956684090030699/posts/8378987530404431634/comments","totalItems":"0"},"selfLink":"https://www.googleapis.com/blogger/v3/blogs/1204956684090030699/posts/8378987530404431634","title":"Retention basin","updated":"2021-03-08T22:38:24-08:00","url":"http://buildingconstructionbl.blogspot.com/2021/01/retention-basin.html"},{"author":{"displayName":"Free Game Puzzles","id":"12243895325069569914","image":{"url":"//www.blogger.com/img/blogger_logo_round_35.png"},"url":"https://www.blogger.com/profile/12243895325069569914"},"blog":{"id":"1204956684090030699"},"content":"","etag":"\"dGltZXN0YW1wOiAxNjE1MjcxOTk2NzczCm9mZnNldDogLTI4ODAwMDAwCg\"","id":"4947319995728285487","kind":"blogger#post","published":"2021-01-11T23:43:00-08:00","replies":{"selfLink":"https://www.googleapis.com/blogger/v3/blogs/1204956684090030699/posts/4947319995728285487/comments","totalItems":"0"},"selfLink":"https://www.googleapis.com/blogger/v3/blogs/1204956684090030699/posts/4947319995728285487","title":"Guy-wire","updated":"2021-03-08T22:39:56-08:00","url":"http://buildingconstructionbl.blogspot.com/2021/01/guy-wire.html"},{"author":{"displayName":"Free Game Puzzles","id":"12243895325069569914","image":{"url":"//www.blogger.com/img/blogger_logo_round_35.png"},"url":"https://www.blogger.com/profile/12243895325069569914"},"blog":{"id":"1204956684090030699"},"content":"","etag":"\"dGltZXN0YW1wOiAxNjE1MjcyMDg1NzU4Cm9mZnNldDogLTI4ODAwMDAwCg\"","id":"8385868520006419476","kind":"blogger#post","published":"2021-01-11T23:30:00-08:00","replies":{"selfLink":"https://www.googleapis.com/blogger/v3/blogs/1204956684090030699/posts/8385868520006419476/comments","totalItems":"0"},"selfLink":"https://www.googleapis.com/blogger/v3/blogs/1204956684090030699/posts/8385868520006419476","title":"Wheelchair ramp","updated":"2021-03-08T22:41:25-08:00","url":"http://buildingconstructionbl.blogspot.com/2021/01/wheelchair-ramp.html"},{"author":{"displayName":"Free Game Puzzles","id":"12243895325069569914","image":{"url":"//www.blogger.com/img/blogger_logo_round_35.png"},"url":"https://www.blogger.com/profile/12243895325069569914"},"blog":{"id":"1204956684090030699"},"content":"","etag":"\"dGltZXN0YW1wOiAxNjExOTkyMTUwNjc5Cm9mZnNldDogLTI4ODAwMDAwCg\"","id":"5631160488247188944","kind":"blogger#post","published":"2021-01-11T23:27:00-08:00","replies":{"selfLink":"https://www.googleapis.com/blogger/v3/blogs/1204956684090030699/posts/5631160488247188944/comments","totalItems":"0"},"selfLink":"https://www.googleapis.com/blogger/v3/blogs/1204956684090030699/posts/5631160488247188944","title":"Partition","updated":"2021-01-29T23:35:50-08:00","url":"http://buildingconstructionbl.blogspot.com/2021/01/partition.html"},{"author":{"displayName":"Free Game Puzzles","id":"12243895325069569914","image":{"url":"//www.blogger.com/img/blogger_logo_round_35.png"},"url":"https://www.blogger.com/profile/12243895325069569914"},"blog":{"id":"1204956684090030699"},"content":"","etag":"\"dGltZXN0YW1wOiAxNjE1MjcyMTY2NjI2Cm9mZnNldDogLTI4ODAwMDAwCg\"","id":"1725420498107858750","kind":"blogger#post","published":"2021-01-11T23:21:00-08:00","replies":{"selfLink":"https://www.googleapis.com/blogger/v3/blogs/1204956684090030699/posts/1725420498107858750/comments","totalItems":"0"},"selfLink":"https://www.googleapis.com/blogger/v3/blogs/1204956684090030699/posts/1725420498107858750","title":"Thin-shell structure","updated":"2021-03-08T22:42:46-08:00","url":"http://buildingconstructionbl.blogspot.com/2021/01/thin-shell-structure.html"},{"author":{"displayName":"Free Game Puzzles","id":"12243895325069569914","image":{"url":"//www.blogger.com/img/blogger_logo_round_35.png"},"url":"https://www.blogger.com/profile/12243895325069569914"},"blog":{"id":"1204956684090030699"},"content":"","etag":"\"dGltZXN0YW1wOiAxNjE1MjcyMjg2MDk0Cm9mZnNldDogLTI4ODAwMDAwCg\"","id":"6433054961123475553","kind":"blogger#post","published":"2021-01-11T23:07:00-08:00","replies":{"selfLink":"https://www.googleapis.com/blogger/v3/blogs/1204956684090030699/posts/6433054961123475553/comments","totalItems":"0"},"selfLink":"https://www.googleapis.com/blogger/v3/blogs/1204956684090030699/posts/6433054961123475553","title":"Handrail","updated":"2021-03-08T22:44:46-08:00","url":"http://buildingconstructionbl.blogspot.com/2021/01/handrail.html"},{"author":{"displayName":"Free Game Puzzles","id":"12243895325069569914","image":{"url":"//www.blogger.com/img/blogger_logo_round_35.png"},"url":"https://www.blogger.com/profile/12243895325069569914"},"blog":{"id":"1204956684090030699"},"content":"","etag":"\"dGltZXN0YW1wOiAxNjE1MjcyNDI5NzUzCm9mZnNldDogLTI4ODAwMDAwCg\"","id":"3080437123968453122","kind":"blogger#post","published":"2021-01-11T22:55:00-08:00","replies":{"selfLink":"https://www.googleapis.com/blogger/v3/blogs/1204956684090030699/posts/3080437123968453122/comments","totalItems":"0"},"selfLink":"https://www.googleapis.com/blogger/v3/blogs/1204956684090030699/posts/3080437123968453122","title":"Pinnacle","updated":"2021-03-08T22:47:09-08:00","url":"http://buildingconstructionbl.blogspot.com/2021/01/pinnacle.html"},{"author":{"displayName":"Free Game Puzzles","id":"12243895325069569914","image":{"url":"//www.blogger.com/img/blogger_logo_round_35.png"},"url":"https://www.blogger.com/profile/12243895325069569914"},"blog":{"id":"1204956684090030699"},"content":"","etag":"\"dGltZXN0YW1wOiAxNjE1MjcyNTM3MDgwCm9mZnNldDogLTI4ODAwMDAwCg\"","id":"1990971289543632353","kind":"blogger#post","published":"2021-01-11T22:31:00-08:00","replies":{"selfLink":"https://www.googleapis.com/blogger/v3/blogs/1204956684090030699/posts/1990971289543632353/comments","totalItems":"0"},"selfLink":"https://www.googleapis.com/blogger/v3/blogs/1204956684090030699/posts/1990971289543632353","title":"Basement","updated":"2021-03-08T22:48:57-08:00","url":"http://buildingconstructionbl.blogspot.com/2021/01/basement.html"},{"author":{"displayName":"Free Game Puzzles","id":"12243895325069569914","image":{"url":"//www.blogger.com/img/blogger_logo_round_35.png"},"url":"https://www.blogger.com/profile/12243895325069569914"},"blog":{"id":"1204956684090030699"},"content":"","etag":"\"dGltZXN0YW1wOiAxNjE1MjczNjcxMjQ0Cm9mZnNldDogLTI4ODAwMDAwCg\"","id":"1546327315028991019","kind":"blogger#post","published":"2021-01-11T10:00:00-08:00","replies":{"selfLink":"https://www.googleapis.com/blogger/v3/blogs/1204956684090030699/posts/1546327315028991019/comments","totalItems":"0"},"selfLink":"https://www.googleapis.com/blogger/v3/blogs/1204956684090030699/posts/1546327315028991019","title":"Floor","updated":"2021-03-08T23:07:51-08:00","url":"http://buildingconstructionbl.blogspot.com/2021/01/floor.html"},{"author":{"displayName":"Free Game Puzzles","id":"12243895325069569914","image":{"url":"//www.blogger.com/img/blogger_logo_round_35.png"},"url":"https://www.blogger.com/profile/12243895325069569914"},"blog":{"id":"1204956684090030699"},"content":"","etag":"\"dGltZXN0YW1wOiAxNjE1MjczNzU5NDgxCm9mZnNldDogLTI4ODAwMDAwCg\"","id":"6644099151009504815","kind":"blogger#post","published":"2021-01-11T09:53:00-08:00","replies":{"selfLink":"https://www.googleapis.com/blogger/v3/blogs/1204956684090030699/posts/6644099151009504815/comments","totalItems":"0"},"selfLink":"https://www.googleapis.com/blogger/v3/blogs/1204956684090030699/posts/6644099151009504815","title":"Engaged column","updated":"2021-03-08T23:09:19-08:00","url":"http://buildingconstructionbl.blogspot.com/2021/01/engaged-column.html"},{"author":{"displayName":"Free Game Puzzles","id":"12243895325069569914","image":{"url":"//www.blogger.com/img/blogger_logo_round_35.png"},"url":"https://www.blogger.com/profile/12243895325069569914"},"blog":{"id":"1204956684090030699"},"content":"","etag":"\"dGltZXN0YW1wOiAxNjE1MjczODQ1MDA4Cm9mZnNldDogLTI4ODAwMDAwCg\"","id":"1053145766428730475","kind":"blogger#post","published":"2021-01-11T09:50:00-08:00","replies":{"selfLink":"https://www.googleapis.com/blogger/v3/blogs/1204956684090030699/posts/1053145766428730475/comments","totalItems":"0"},"selfLink":"https://www.googleapis.com/blogger/v3/blogs/1204956684090030699/posts/1053145766428730475","title":"Lintel","updated":"2021-03-08T23:10:45-08:00","url":"http://buildingconstructionbl.blogspot.com/2021/01/lintel.html"},{"author":{"displayName":"Free Game Puzzles","id":"12243895325069569914","image":{"url":"//www.blogger.com/img/blogger_logo_round_35.png"},"url":"https://www.blogger.com/profile/12243895325069569914"},"blog":{"id":"1204956684090030699"},"content":"","etag":"\"dGltZXN0YW1wOiAxNjE1Mjc0MDM2MTQ3Cm9mZnNldDogLTI4ODAwMDAwCg\"","id":"4778434966860650944","kind":"blogger#post","published":"2021-01-11T09:37:00-08:00","replies":{"selfLink":"https://www.googleapis.com/blogger/v3/blogs/1204956684090030699/posts/4778434966860650944/comments","totalItems":"0"},"selfLink":"https://www.googleapis.com/blogger/v3/blogs/1204956684090030699/posts/4778434966860650944","title":"Purlin","updated":"2021-03-08T23:13:56-08:00","url":"http://buildingconstructionbl.blogspot.com/2021/01/purlin.html"},{"author":{"displayName":"Free Game Puzzles","id":"12243895325069569914","image":{"url":"//www.blogger.com/img/blogger_logo_round_35.png"},"url":"https://www.blogger.com/profile/12243895325069569914"},"blog":{"id":"1204956684090030699"},"content":"","etag":"\"dGltZXN0YW1wOiAxNjE1Mjc0MTc2ODA5Cm9mZnNldDogLTI4ODAwMDAwCg\"","id":"6088770730339702545","kind":"blogger#post","published":"2021-01-11T09:30:00-08:00","replies":{"selfLink":"https://www.googleapis.com/blogger/v3/blogs/1204956684090030699/posts/6088770730339702545/comments","totalItems":"0"},"selfLink":"https://www.googleapis.com/blogger/v3/blogs/1204956684090030699/posts/6088770730339702545","title":"Distribution board","updated":"2021-03-08T23:16:16-08:00","url":"http://buildingconstructionbl.blogspot.com/2021/01/distribution-board.html"},{"author":{"displayName":"Free Game Puzzles","id":"12243895325069569914","image":{"url":"//www.blogger.com/img/blogger_logo_round_35.png"},"url":"https://www.blogger.com/profile/12243895325069569914"},"blog":{"id":"1204956684090030699"},"content":"","etag":"\"dGltZXN0YW1wOiAxNjE1Mjc0MjQ5NTkwCm9mZnNldDogLTI4ODAwMDAwCg\"","id":"1221378725730627798","kind":"blogger#post","published":"2021-01-11T09:21:00-08:00","replies":{"selfLink":"https://www.googleapis.com/blogger/v3/blogs/1204956684090030699/posts/1221378725730627798/comments","totalItems":"0"},"selfLink":"https://www.googleapis.com/blogger/v3/blogs/1204956684090030699/posts/1221378725730627798","title":"Gridshell","updated":"2021-03-08T23:17:29-08:00","url":"http://buildingconstructionbl.blogspot.com/2021/01/gridshell.html"},{"author":{"displayName":"Free Game Puzzles","id":"12243895325069569914","image":{"url":"//www.blogger.com/img/blogger_logo_round_35.png"},"url":"https://www.blogger.com/profile/12243895325069569914"},"blog":{"id":"1204956684090030699"},"content":"","etag":"\"dGltZXN0YW1wOiAxNjE1Mjc0MzIyNjA3Cm9mZnNldDogLTI4ODAwMDAwCg\"","id":"692935987905383325","kind":"blogger#post","published":"2021-01-11T09:14:00-08:00","replies":{"selfLink":"https://www.googleapis.com/blogger/v3/blogs/1204956684090030699/posts/692935987905383325/comments","totalItems":"0"},"selfLink":"https://www.googleapis.com/blogger/v3/blogs/1204956684090030699/posts/692935987905383325","title":"Crib pier","updated":"2021-03-08T23:18:42-08:00","url":"http://buildingconstructionbl.blogspot.com/2021/01/crib-pier.html"},{"author":{"displayName":"Free Game Puzzles","id":"12243895325069569914","image":{"url":"//www.blogger.com/img/blogger_logo_round_35.png"},"url":"https://www.blogger.com/profile/12243895325069569914"},"blog":{"id":"1204956684090030699"},"content":"","etag":"\"dGltZXN0YW1wOiAxNjE1Mjc0NDI4MzIzCm9mZnNldDogLTI4ODAwMDAwCg\"","id":"7290917210734957481","kind":"blogger#post","published":"2021-01-11T09:06:00-08:00","replies":{"selfLink":"https://www.googleapis.com/blogger/v3/blogs/1204956684090030699/posts/7290917210734957481/comments","totalItems":"0"},"selfLink":"https://www.googleapis.com/blogger/v3/blogs/1204956684090030699/posts/7290917210734957481","title":"Vault (architecture)","updated":"2021-03-08T23:20:28-08:00","url":"http://buildingconstructionbl.blogspot.com/2021/01/vault-architecture.html"},{"author":{"displayName":"Free Game Puzzles","id":"12243895325069569914","image":{"url":"//www.blogger.com/img/blogger_logo_round_35.png"},"url":"https://www.blogger.com/profile/12243895325069569914"},"blog":{"id":"1204956684090030699"},"content":"","etag":"\"dGltZXN0YW1wOiAxNjE1Mjc0NTI1MjY5Cm9mZnNldDogLTI4ODAwMDAwCg\"","id":"2222889505771086810","kind":"blogger#post","published":"2021-01-11T08:42:00-08:00","replies":{"selfLink":"https://www.googleapis.com/blogger/v3/blogs/1204956684090030699/posts/2222889505771086810/comments","totalItems":"0"},"selfLink":"https://www.googleapis.com/blogger/v3/blogs/1204956684090030699/posts/2222889505771086810","title":"Log cabin","updated":"2021-03-08T23:22:05-08:00","url":"http://buildingconstructionbl.blogspot.com/2021/01/log-cabin.html"},{"author":{"displayName":"Free Game Puzzles","id":"12243895325069569914","image":{"url":"//www.blogger.com/img/blogger_logo_round_35.png"},"url":"https://www.blogger.com/profile/12243895325069569914"},"blog":{"id":"1204956684090030699"},"content":"","etag":"\"dGltZXN0YW1wOiAxNjEwMzgyOTUyNzEwCm9mZnNldDogLTI4ODAwMDAwCg\"","id":"9052783663325043630","kind":"blogger#post","published":"2021-01-11T08:35:00-08:00","replies":{"selfLink":"https://www.googleapis.com/blogger/v3/blogs/1204956684090030699/posts/9052783663325043630/comments","totalItems":"0"},"selfLink":"https://www.googleapis.com/blogger/v3/blogs/1204956684090030699/posts/9052783663325043630","title":"Scaffolding","updated":"2021-01-11T08:35:52-08:00","url":"http://buildingconstructionbl.blogspot.com/2021/01/scaffolding.html"},{"author":{"displayName":"Free Game Puzzles","id":"12243895325069569914","image":{"url":"//www.blogger.com/img/blogger_logo_round_35.png"},"url":"https://www.blogger.com/profile/12243895325069569914"},"blog":{"id":"1204956684090030699"},"content":"","etag":"\"dGltZXN0YW1wOiAxNjE1Mjc0NjA1Mjg0Cm9mZnNldDogLTI4ODAwMDAwCg\"","id":"1276727082149379513","kind":"blogger#post","published":"2021-01-11T08:24:00-08:00","replies":{"selfLink":"https://www.googleapis.com/blogger/v3/blogs/1204956684090030699/posts/1276727082149379513/comments","totalItems":"0"},"selfLink":"https://www.googleapis.com/blogger/v3/blogs/1204956684090030699/posts/1276727082149379513","title":"Rafter","updated":"2021-03-08T23:23:25-08:00","url":"http://buildingconstructionbl.blogspot.com/2021/01/rafter.html"},{"author":{"displayName":"Free Game Puzzles","id":"12243895325069569914","image":{"url":"//www.blogger.com/img/blogger_logo_round_35.png"},"url":"https://www.blogger.com/profile/12243895325069569914"},"blog":{"id":"1204956684090030699"},"content":"","etag":"\"dGltZXN0YW1wOiAxNjE1Mjc0NjgyOTIzCm9mZnNldDogLTI4ODAwMDAwCg\"","id":"2545259894445587882","kind":"blogger#post","published":"2021-01-11T08:18:00-08:00","replies":{"selfLink":"https://www.googleapis.com/blogger/v3/blogs/1204956684090030699/posts/2545259894445587882/comments","totalItems":"0"},"selfLink":"https://www.googleapis.com/blogger/v3/blogs/1204956684090030699/posts/2545259894445587882","title":"Screed","updated":"2021-03-08T23:24:42-08:00","url":"http://buildingconstructionbl.blogspot.com/2021/01/screed.html"},{"author":{"displayName":"Free Game Puzzles","id":"12243895325069569914","image":{"url":"//www.blogger.com/img/blogger_logo_round_35.png"},"url":"https://www.blogger.com/profile/12243895325069569914"},"blog":{"id":"1204956684090030699"},"content":"","etag":"\"dGltZXN0YW1wOiAxNjE1Mjc0ODI4MDQzCm9mZnNldDogLTI4ODAwMDAwCg\"","id":"3543612070238985939","kind":"blogger#post","published":"2021-01-11T07:55:00-08:00","replies":{"selfLink":"https://www.googleapis.com/blogger/v3/blogs/1204956684090030699/posts/3543612070238985939/comments","totalItems":"0"},"selfLink":"https://www.googleapis.com/blogger/v3/blogs/1204956684090030699/posts/3543612070238985939","title":"Triforium","updated":"2021-03-08T23:27:08-08:00","url":"http://buildingconstructionbl.blogspot.com/2021/01/triforium.html"},{"author":{"displayName":"Free Game Puzzles","id":"12243895325069569914","image":{"url":"//www.blogger.com/img/blogger_logo_round_35.png"},"url":"https://www.blogger.com/profile/12243895325069569914"},"blog":{"id":"1204956684090030699"},"content":"","etag":"\"dGltZXN0YW1wOiAxNjE1Mjc0OTI1NDIwCm9mZnNldDogLTI4ODAwMDAwCg\"","id":"3756266536257965443","kind":"blogger#post","published":"2021-01-11T07:46:00-08:00","replies":{"selfLink":"https://www.googleapis.com/blogger/v3/blogs/1204956684090030699/posts/3756266536257965443/comments","totalItems":"0"},"selfLink":"https://www.googleapis.com/blogger/v3/blogs/1204956684090030699/posts/3756266536257965443","title":"Raised floor","updated":"2021-03-08T23:28:45-08:00","url":"http://buildingconstructionbl.blogspot.com/2021/01/raised-floor.html"},{"author":{"displayName":"Free Game Puzzles","id":"12243895325069569914","image":{"url":"//www.blogger.com/img/blogger_logo_round_35.png"},"url":"https://www.blogger.com/profile/12243895325069569914"},"blog":{"id":"1204956684090030699"},"content":"","etag":"\"dGltZXN0YW1wOiAxNjE1Mjc1MTYwODkyCm9mZnNldDogLTI4ODAwMDAwCg\"","id":"3348899329537206410","kind":"blogger#post","published":"2021-01-11T07:42:00-08:00","replies":{"selfLink":"https://www.googleapis.com/blogger/v3/blogs/1204956684090030699/posts/3348899329537206410/comments","totalItems":"0"},"selfLink":"https://www.googleapis.com/blogger/v3/blogs/1204956684090030699/posts/3348899329537206410","title":"Truss","updated":"2021-03-08T23:32:40-08:00","url":"http://buildingconstructionbl.blogspot.com/2021/01/truss.html"},{"author":{"displayName":"Free Game Puzzles","id":"12243895325069569914","image":{"url":"//www.blogger.com/img/blogger_logo_round_35.png"},"url":"https://www.blogger.com/profile/12243895325069569914"},"blog":{"id":"1204956684090030699"},"content":"","etag":"\"dGltZXN0YW1wOiAxNjE1Mjc1Mjc1ODc1Cm9mZnNldDogLTI4ODAwMDAwCg\"","id":"8569161810033935683","kind":"blogger#post","published":"2021-01-11T07:36:00-08:00","replies":{"selfLink":"https://www.googleapis.com/blogger/v3/blogs/1204956684090030699/posts/8569161810033935683/comments","totalItems":"0"},"selfLink":"https://www.googleapis.com/blogger/v3/blogs/1204956684090030699/posts/8569161810033935683","title":"Foundation (engineering)","updated":"2021-03-08T23:34:35-08:00","url":"http://buildingconstructionbl.blogspot.com/2021/01/foundation-engineering.html"},{"author":{"displayName":"Free Game Puzzles","id":"12243895325069569914","image":{"url":"//www.blogger.com/img/blogger_logo_round_35.png"},"url":"https://www.blogger.com/profile/12243895325069569914"},"blog":{"id":"1204956684090030699"},"content":"","etag":"\"dGltZXN0YW1wOiAxNjE1Mjc1MzU3ODc5Cm9mZnNldDogLTI4ODAwMDAwCg\"","id":"4717468315844454946","kind":"blogger#post","published":"2021-01-11T07:27:00-08:00","replies":{"selfLink":"https://www.googleapis.com/blogger/v3/blogs/1204956684090030699/posts/4717468315844454946/comments","totalItems":"0"},"selfLink":"https://www.googleapis.com/blogger/v3/blogs/1204956684090030699/posts/4717468315844454946","title":"Cyclopean masonry","updated":"2021-03-08T23:35:57-08:00","url":"http://buildingconstructionbl.blogspot.com/2021/01/cyclopean-masonry.html"},{"author":{"displayName":"Free Game Puzzles","id":"12243895325069569914","image":{"url":"//www.blogger.com/img/blogger_logo_round_35.png"},"url":"https://www.blogger.com/profile/12243895325069569914"},"blog":{"id":"1204956684090030699"},"content":"","etag":"\"dGltZXN0YW1wOiAxNjE1Mjc1NDMzOTIyCm9mZnNldDogLTI4ODAwMDAwCg\"","id":"7331008080496206936","kind":"blogger#post","published":"2021-01-11T07:23:00-08:00","replies":{"selfLink":"https://www.googleapis.com/blogger/v3/blogs/1204956684090030699/posts/7331008080496206936/comments","totalItems":"0"},"selfLink":"https://www.googleapis.com/blogger/v3/blogs/1204956684090030699/posts/7331008080496206936","title":"Semi-basement","updated":"2021-03-08T23:37:13-08:00","url":"http://buildingconstructionbl.blogspot.com/2021/01/semi-basement.html"},{"author":{"displayName":"Free Game Puzzles","id":"12243895325069569914","image":{"url":"//www.blogger.com/img/blogger_logo_round_35.png"},"url":"https://www.blogger.com/profile/12243895325069569914"},"blog":{"id":"1204956684090030699"},"content":"","etag":"\"dGltZXN0YW1wOiAxNjExOTkyMjEyOTYyCm9mZnNldDogLTI4ODAwMDAwCg\"","id":"3074926299144685238","kind":"blogger#post","published":"2021-01-11T07:18:00-08:00","replies":{"selfLink":"https://www.googleapis.com/blogger/v3/blogs/1204956684090030699/posts/3074926299144685238/comments","totalItems":"0"},"selfLink":"https://www.googleapis.com/blogger/v3/blogs/1204956684090030699/posts/3074926299144685238","title":"Structural channel","updated":"2021-01-29T23:36:52-08:00","url":"http://buildingconstructionbl.blogspot.com/2021/01/structural-channel.html"},{"author":{"displayName":"Free Game Puzzles","id":"12243895325069569914","image":{"url":"//www.blogger.com/img/blogger_logo_round_35.png"},"url":"https://www.blogger.com/profile/12243895325069569914"},"blog":{"id":"1204956684090030699"},"content":"","etag":"\"dGltZXN0YW1wOiAxNjE1Mjc1NTA2MTk3Cm9mZnNldDogLTI4ODAwMDAwCg\"","id":"4200396848101508301","kind":"blogger#post","published":"2021-01-11T07:11:00-08:00","replies":{"selfLink":"https://www.googleapis.com/blogger/v3/blogs/1204956684090030699/posts/4200396848101508301/comments","totalItems":"0"},"selfLink":"https://www.googleapis.com/blogger/v3/blogs/1204956684090030699/posts/4200396848101508301","title":"Grout","updated":"2021-03-08T23:38:26-08:00","url":"http://buildingconstructionbl.blogspot.com/2021/01/grout-from-wikipedia-free-encyclopedia.html"},{"author":{"displayName":"Free Game Puzzles","id":"12243895325069569914","image":{"url":"//www.blogger.com/img/blogger_logo_round_35.png"},"url":"https://www.blogger.com/profile/12243895325069569914"},"blog":{"id":"1204956684090030699"},"content":"","etag":"\"dGltZXN0YW1wOiAxNjEwMzc3NDk0ODQxCm9mZnNldDogLTI4ODAwMDAwCg\"","id":"6609911918141696330","kind":"blogger#post","published":"2021-01-11T07:04:00-08:00","replies":{"selfLink":"https://www.googleapis.com/blogger/v3/blogs/1204956684090030699/posts/6609911918141696330/comments","totalItems":"0"},"selfLink":"https://www.googleapis.com/blogger/v3/blogs/1204956684090030699/posts/6609911918141696330","title":"Bay window","updated":"2021-01-11T07:04:54-08:00","url":"http://buildingconstructionbl.blogspot.com/2021/01/bay-window.html"},{"author":{"displayName":"Free Game Puzzles","id":"12243895325069569914","image":{"url":"//www.blogger.com/img/blogger_logo_round_35.png"},"url":"https://www.blogger.com/profile/12243895325069569914"},"blog":{"id":"1204956684090030699"},"content":"","etag":"\"dGltZXN0YW1wOiAxNjE1Mjc1NjEzMTM4Cm9mZnNldDogLTI4ODAwMDAwCg\"","id":"6911126064547781549","kind":"blogger#post","published":"2021-01-11T07:00:00-08:00","replies":{"selfLink":"https://www.googleapis.com/blogger/v3/blogs/1204956684090030699/posts/6911126064547781549/comments","totalItems":"0"},"selfLink":"https://www.googleapis.com/blogger/v3/blogs/1204956684090030699/posts/6911126064547781549","title":"Stage lighting instrument","updated":"2021-03-08T23:40:13-08:00","url":"http://buildingconstructionbl.blogspot.com/2021/01/stage-lighting-instrument.html"},{"author":{"displayName":"Free Game Puzzles","id":"12243895325069569914","image":{"url":"//www.blogger.com/img/blogger_logo_round_35.png"},"url":"https://www.blogger.com/profile/12243895325069569914"},"blog":{"id":"1204956684090030699"},"content":"","etag":"\"dGltZXN0YW1wOiAxNjEwOTYwMzYzNDIzCm9mZnNldDogLTI4ODAwMDAwCg\"","id":"5034144931800404515","kind":"blogger#post","published":"2021-01-11T06:52:00-08:00","replies":{"selfLink":"https://www.googleapis.com/blogger/v3/blogs/1204956684090030699/posts/5034144931800404515/comments","totalItems":"0"},"selfLink":"https://www.googleapis.com/blogger/v3/blogs/1204956684090030699/posts/5034144931800404515","title":"Automotive molding","updated":"2021-01-18T00:59:23-08:00","url":"http://buildingconstructionbl.blogspot.com/2021/01/automotive-molding.html"}],"etag":"\"MjAyMS0wMy0wOVQwNzo0MDoxMy4xMzha\""}
